awsipcheck/__init__.py
awsipcheck/__main__.py
awsipcheck/cli.py
awsipcheck/core.py
awsipcheck-7.0.dist-info/LICENSE
awsipcheck-7.0.dist-info/METADATA
awsipcheck-7.0.dist-info/WHEEL
awsipcheck-7.0.dist-info/entry_points.txt
awsipcheck-7.0.dist-info/top_level.txt
awsipcheck-7.0.dist-info/RECORD
